docx_ea_font-0.0.1.dist-info/METADATA
docx_ea_font-0.0.1.dist-info/WHEEL
docx_ea_font-0.0.1.dist-info/entry_points.txt
docx_ea_font-0.0.1.dist-info/licenses/LICENSE
docx_ea_font/__init__.py
docx_ea_font-0.0.1.dist-info/RECORD
