Metadata-Version: 2.1
Name: docx-ea-font
Version: 0.0.1
Summary: Set east asia font in docx correctly.
Author-Email: MakerBi <andersonby@163.com>
License: MIT
Classifier: Programming Language :: Python :: 3
Classifier: License :: OSI Approved :: MIT License
Classifier: Operating System :: OS Independent
Project-URL: Homepage, https://github.com/AndersonBY/docx-ea-font
Requires-Python: >=3.8
Requires-Dist: python-docx
